{
  "cli": {
    "version": ">= 7.0.0"
  },
  "build": {
    "development": {
      "developmentClient": true,
      "distribution": "internal",
      "env": {
        "NPM_INSTALL_ARGS": "--legacy-peer-deps"
      }
    },
    "preview": {
      "distribution": "internal",
      "android": {
        "buildType": "apk"
      },
      "env": {
        "NPM_INSTALL_ARGS": "--legacy-peer-deps",
        "EXPO_PUBLIC_API_URL": "https://playground-management-nal2.onrender.com"
      }
    },
    "production": {
      "android": {
        "buildType": "app-bundle"
      },
      "env": {
        "NPM_INSTALL_ARGS": "--legacy-peer-deps",
        "EXPO_PUBLIC_API_URL": "https://playground-management-nal2.onrender.com"
      }
    }
  },
  "submit": {
    "production": {}
  }
}
